pymatting/__about__.py
pymatting/__init__.py
pymatting/alpha/__init__.py
pymatting/alpha/estimate_alpha_cf.py
pymatting/alpha/estimate_alpha_knn.py
pymatting/alpha/estimate_alpha_lbdm.py
pymatting/alpha/estimate_alpha_lkm.py
pymatting/alpha/estimate_alpha_rw.py
pymatting/alpha/estimate_alpha_sm.py
pymatting/config/__init__.py
pymatting/cutout/__init__.py
pymatting/cutout/cutout.py
pymatting/foreground/__init__.py
pymatting/foreground/estimate_foreground_cf.py
pymatting/foreground/estimate_foreground_ml.py
pymatting/foreground/estimate_foreground_ml_cupy.py
pymatting/foreground/estimate_foreground_ml_pyopencl.py
pymatting/laplacian/__init__.py
pymatting/laplacian/cf_laplacian.py
pymatting/laplacian/knn_laplacian.py
pymatting/laplacian/laplacian.py
pymatting/laplacian/lbdm_laplacian.py
pymatting/laplacian/lkm_laplacian.py
pymatting/laplacian/rw_laplacian.py
pymatting/laplacian/uniform_laplacian.py
pymatting/preconditioner/__init__.py
pymatting/preconditioner/ichol.py
pymatting/preconditioner/jacobi.py
pymatting/preconditioner/vcycle.py
pymatting/solver/__init__.py
pymatting/solver/callback.py
pymatting/solver/cg.py
pymatting/util/__init__.py
pymatting/util/boxfilter.py
pymatting/util/distance.py
pymatting/util/kdtree.py
pymatting/util/timer.py
pymatting/util/util.py
PyMatting-1.1.13.dist-info/LICENSE.md
PyMatting-1.1.13.dist-info/METADATA
PyMatting-1.1.13.dist-info/WHEEL
PyMatting-1.1.13.dist-info/top_level.txt
PyMatting-1.1.13.dist-info/RECORD
