Metadata-Version: 2.1
Name: PyMatting
Version: 1.1.13
Summary: Python package for alpha matting.
Home-page: https://pymatting.github.io
Author: The PyMatting Developers
Author-email: pymatting@gmail.com
License: MIT
Project-URL: Source, https://github.com/pymatting/pymatting
Keywords: alpha matting
Classifier: Programming Language :: Python :: 3
Classifier: License :: OSI Approved :: MIT License
Classifier: Operating System :: OS Independent
Requires-Python: >=3
License-File: LICENSE.md
Requires-Dist: numpy>=1.16.0
Requires-Dist: pillow>=5.2.0
Requires-Dist: numba!=0.49.0
Requires-Dist: scipy>=1.1.0
